pycarol/__init__.py
pycarol/apps.py
pycarol/bigquery.py
pycarol/carol.py
pycarol/carol_api.py
pycarol/carolina.py
pycarol/cds.py
pycarol/compute.py
pycarol/connectors.py
pycarol/exceptions.py
pycarol/filter.py
pycarol/logger.py
pycarol/named_query.py
pycarol/organization.py
pycarol/query.py
pycarol/schema_generator.py
pycarol/staging.py
pycarol/storage.py
pycarol/subscription.py
pycarol/tasks.py
pycarol/tenant.py
pycarol/verticals.py
pycarol/app/__init__.py
pycarol/app/health_check_online.py
pycarol/app/logger.py
pycarol/app/manifest_parser.py
pycarol/app/manifest_validator.py
pycarol/app/online.py
pycarol/app/online_api.py
pycarol/app/online_request.py
pycarol/app/redis_target.py
pycarol/auth/ApiKeyAuth.py
pycarol/auth/ApiKeyAuth_cloner.py
pycarol/auth/PwdAuth.py
pycarol/auth/PwdAuth_cloner.py
pycarol/auth/PwdFluig.py
pycarol/auth/PwdKeyAuth.py
pycarol/auth/__init__.py
pycarol/data_models/__init__.py
pycarol/data_models/data_model_build.py
pycarol/data_models/data_model_types.py
pycarol/data_models/data_models.py
pycarol/data_models/data_models_fields.py
pycarol/functions/__init__.py
pycarol/functions/misc.py
pycarol/luigi_extension/__init__.py
pycarol/luigi_extension/targets.py
pycarol/luigi_extension/task.py
pycarol/pipeline/__init__.py
pycarol/pipeline/conftest.py
pycarol/pipeline/targets/__init__.py
pycarol/pipeline/targets/deprecated_targets.py
pycarol/pipeline/targets/targets.py
pycarol/pipeline/targets/test_task_target.py
pycarol/pipeline/task/__init__.py
pycarol/pipeline/task/dockertask.py
pycarol/pipeline/task/kubernetestask.py
pycarol/pipeline/task/task.py
pycarol/pipeline/task/test_task.py
pycarol/pipeline/test/__init__.py
pycarol/pipeline/test/test.py
pycarol/pipeline/tools/__init__.py
pycarol/pipeline/tools/_tools.py
pycarol/pipeline/tools/pipeline_example.py
pycarol/pipeline/tools/test_tools.py
pycarol/pipeline/utils/__init__.py
pycarol/pipeline/utils/_utils.py
pycarol/pipeline/utils/test_utils.py
pycarol/pipeline/utils/hash_versioning/__init__.py
pycarol-2.56.1.dist-info/METADATA
pycarol-2.56.1.dist-info/WHEEL
pycarol-2.56.1.dist-info/top_level.txt
pycarol-2.56.1.dist-info/RECORD
