Metadata-Version: 2.1
Name: pycarol
Version: 2.56.1
Summary: Carol Python API and Tools
Home-page: https://github.com/totvslabs/pyCarol
Author: TotvsLabs
Author-email: ops@totvslabs.com
Maintainer: TOTVS Labs
License: TOTVS
Keywords: Totvs,Carol.ai,AI
Classifier: Development Status :: 5 - Production/Stable
Classifier: Intended Audience :: Developers
Classifier: Topic :: Software Development :: Build Tools
Classifier: License :: OSI Approved :: MIT License
Classifier: Programming Language :: Python :: 3.6
Classifier: Operating System :: OS Independent
Requires-Dist: beautifulsoup4
Requires-Dist: deprecated
Requires-Dist: deprecation
Requires-Dist: gcsfs<0.7,>=0.3.0
Requires-Dist: google-auth
Requires-Dist: google-auth-httplib2
Requires-Dist: google-cloud-bigquery>=2.26.0
Requires-Dist: google-cloud-bigquery-storage
Requires-Dist: google-cloud-core>=1.4.1
Requires-Dist: google-cloud-storage
Requires-Dist: python-dotenv
Requires-Dist: requests
Requires-Dist: retry
Requires-Dist: tqdm
Requires-Dist: urllib3
Requires-Dist: pandas!=1.0.4,>=0.23.4
Requires-Dist: numpy>=1.16.3
Requires-Dist: pip-system-certs
Provides-Extra: complete
Requires-Dist: beautifulsoup4; extra == "complete"
Requires-Dist: black; extra == "complete"
Requires-Dist: dask[complete]; extra == "complete"
Requires-Dist: deprecated; extra == "complete"
Requires-Dist: deprecation; extra == "complete"
Requires-Dist: flake8; extra == "complete"
Requires-Dist: flask>=1.0.2; extra == "complete"
Requires-Dist: gcsfs<0.7,>=0.3.0; extra == "complete"
Requires-Dist: google-auth; extra == "complete"
Requires-Dist: google-auth-httplib2; extra == "complete"
Requires-Dist: google-cloud-bigquery-storage; extra == "complete"
Requires-Dist: google-cloud-bigquery>=2.26.0; extra == "complete"
Requires-Dist: google-cloud-core>=1.4.1; extra == "complete"
Requires-Dist: google-cloud-storage; extra == "complete"
Requires-Dist: joblib>=0.11; extra == "complete"
Requires-Dist: luigi; extra == "complete"
Requires-Dist: mypy; extra == "complete"
Requires-Dist: numpy>=1.16.3; extra == "complete"
Requires-Dist: pandas!=1.0.4,>=0.23.4; extra == "complete"
Requires-Dist: papermill; extra == "complete"
Requires-Dist: pip-system-certs; extra == "complete"
Requires-Dist: pyarrow<1.0.0,>=0.15.1; extra == "complete"
Requires-Dist: pydocstyle; extra == "complete"
Requires-Dist: pylint; extra == "complete"
Requires-Dist: pytest; extra == "complete"
Requires-Dist: python-dotenv; extra == "complete"
Requires-Dist: redis; extra == "complete"
Requires-Dist: requests; extra == "complete"
Requires-Dist: retry; extra == "complete"
Requires-Dist: sphinx; extra == "complete"
Requires-Dist: sphinx-rtd-theme; extra == "complete"
Requires-Dist: tqdm; extra == "complete"
Requires-Dist: types-requests; extra == "complete"
Requires-Dist: urllib3; extra == "complete"
Provides-Extra: dask
Requires-Dist: beautifulsoup4; extra == "dask"
Requires-Dist: deprecated; extra == "dask"
Requires-Dist: deprecation; extra == "dask"
Requires-Dist: gcsfs<0.7,>=0.3.0; extra == "dask"
Requires-Dist: google-auth; extra == "dask"
Requires-Dist: google-auth-httplib2; extra == "dask"
Requires-Dist: google-cloud-bigquery>=2.26.0; extra == "dask"
Requires-Dist: google-cloud-bigquery-storage; extra == "dask"
Requires-Dist: google-cloud-core>=1.4.1; extra == "dask"
Requires-Dist: google-cloud-storage; extra == "dask"
Requires-Dist: python-dotenv; extra == "dask"
Requires-Dist: requests; extra == "dask"
Requires-Dist: retry; extra == "dask"
Requires-Dist: tqdm; extra == "dask"
Requires-Dist: urllib3; extra == "dask"
Requires-Dist: pandas!=1.0.4,>=0.23.4; extra == "dask"
Requires-Dist: numpy>=1.16.3; extra == "dask"
Requires-Dist: pip-system-certs; extra == "dask"
Requires-Dist: dask[complete]; extra == "dask"
Provides-Extra: dataframe
Requires-Dist: beautifulsoup4; extra == "dataframe"
Requires-Dist: deprecated; extra == "dataframe"
Requires-Dist: deprecation; extra == "dataframe"
Requires-Dist: gcsfs<0.7,>=0.3.0; extra == "dataframe"
Requires-Dist: google-auth; extra == "dataframe"
Requires-Dist: google-auth-httplib2; extra == "dataframe"
Requires-Dist: google-cloud-bigquery>=2.26.0; extra == "dataframe"
Requires-Dist: google-cloud-bigquery-storage; extra == "dataframe"
Requires-Dist: google-cloud-core>=1.4.1; extra == "dataframe"
Requires-Dist: google-cloud-storage; extra == "dataframe"
Requires-Dist: python-dotenv; extra == "dataframe"
Requires-Dist: requests; extra == "dataframe"
Requires-Dist: retry; extra == "dataframe"
Requires-Dist: tqdm; extra == "dataframe"
Requires-Dist: urllib3; extra == "dataframe"
Requires-Dist: pandas!=1.0.4,>=0.23.4; extra == "dataframe"
Requires-Dist: numpy>=1.16.3; extra == "dataframe"
Requires-Dist: pip-system-certs; extra == "dataframe"
Requires-Dist: joblib>=0.11; extra == "dataframe"
Requires-Dist: pyarrow<1.0.0,>=0.15.1; extra == "dataframe"
Provides-Extra: dev
Requires-Dist: beautifulsoup4; extra == "dev"
Requires-Dist: deprecated; extra == "dev"
Requires-Dist: deprecation; extra == "dev"
Requires-Dist: gcsfs<0.7,>=0.3.0; extra == "dev"
Requires-Dist: google-auth; extra == "dev"
Requires-Dist: google-auth-httplib2; extra == "dev"
Requires-Dist: google-cloud-bigquery>=2.26.0; extra == "dev"
Requires-Dist: google-cloud-bigquery-storage; extra == "dev"
Requires-Dist: google-cloud-core>=1.4.1; extra == "dev"
Requires-Dist: google-cloud-storage; extra == "dev"
Requires-Dist: python-dotenv; extra == "dev"
Requires-Dist: requests; extra == "dev"
Requires-Dist: retry; extra == "dev"
Requires-Dist: tqdm; extra == "dev"
Requires-Dist: urllib3; extra == "dev"
Requires-Dist: pandas!=1.0.4,>=0.23.4; extra == "dev"
Requires-Dist: numpy>=1.16.3; extra == "dev"
Requires-Dist: pip-system-certs; extra == "dev"
Requires-Dist: black; extra == "dev"
Requires-Dist: flake8; extra == "dev"
Requires-Dist: mypy; extra == "dev"
Requires-Dist: pydocstyle; extra == "dev"
Requires-Dist: pylint; extra == "dev"
Requires-Dist: pytest; extra == "dev"
Requires-Dist: sphinx-rtd-theme; extra == "dev"
Requires-Dist: sphinx; extra == "dev"
Requires-Dist: types-requests; extra == "dev"
Provides-Extra: onlineapp
Requires-Dist: beautifulsoup4; extra == "onlineapp"
Requires-Dist: deprecated; extra == "onlineapp"
Requires-Dist: deprecation; extra == "onlineapp"
Requires-Dist: gcsfs<0.7,>=0.3.0; extra == "onlineapp"
Requires-Dist: google-auth; extra == "onlineapp"
Requires-Dist: google-auth-httplib2; extra == "onlineapp"
Requires-Dist: google-cloud-bigquery>=2.26.0; extra == "onlineapp"
Requires-Dist: google-cloud-bigquery-storage; extra == "onlineapp"
Requires-Dist: google-cloud-core>=1.4.1; extra == "onlineapp"
Requires-Dist: google-cloud-storage; extra == "onlineapp"
Requires-Dist: python-dotenv; extra == "onlineapp"
Requires-Dist: requests; extra == "onlineapp"
Requires-Dist: retry; extra == "onlineapp"
Requires-Dist: tqdm; extra == "onlineapp"
Requires-Dist: urllib3; extra == "onlineapp"
Requires-Dist: pandas!=1.0.4,>=0.23.4; extra == "onlineapp"
Requires-Dist: numpy>=1.16.3; extra == "onlineapp"
Requires-Dist: pip-system-certs; extra == "onlineapp"
Requires-Dist: flask>=1.0.2; extra == "onlineapp"
Requires-Dist: redis; extra == "onlineapp"
Provides-Extra: pipeline
Requires-Dist: beautifulsoup4; extra == "pipeline"
Requires-Dist: deprecated; extra == "pipeline"
Requires-Dist: deprecation; extra == "pipeline"
Requires-Dist: gcsfs<0.7,>=0.3.0; extra == "pipeline"
Requires-Dist: google-auth; extra == "pipeline"
Requires-Dist: google-auth-httplib2; extra == "pipeline"
Requires-Dist: google-cloud-bigquery>=2.26.0; extra == "pipeline"
Requires-Dist: google-cloud-bigquery-storage; extra == "pipeline"
Requires-Dist: google-cloud-core>=1.4.1; extra == "pipeline"
Requires-Dist: google-cloud-storage; extra == "pipeline"
Requires-Dist: python-dotenv; extra == "pipeline"
Requires-Dist: requests; extra == "pipeline"
Requires-Dist: retry; extra == "pipeline"
Requires-Dist: tqdm; extra == "pipeline"
Requires-Dist: urllib3; extra == "pipeline"
Requires-Dist: pandas!=1.0.4,>=0.23.4; extra == "pipeline"
Requires-Dist: numpy>=1.16.3; extra == "pipeline"
Requires-Dist: pip-system-certs; extra == "pipeline"
Requires-Dist: joblib>=0.11; extra == "pipeline"
Requires-Dist: pyarrow<1.0.0,>=0.15.1; extra == "pipeline"
Requires-Dist: luigi; extra == "pipeline"
Requires-Dist: papermill; extra == "pipeline"
